vivs/__init__.py
vivs/_constants.py
vivs/_dl_utils.py
vivs/_models.py
vivs/_training.py
vivs/_utils.py
vivs/_vivs.py
vivs-0.1.1.dist-info/LICENSE
vivs-0.1.1.dist-info/METADATA
vivs-0.1.1.dist-info/WHEEL
vivs-0.1.1.dist-info/RECORD
