Metadata-Version: 2.1
Name: vivs
Version: 0.1.1
Summary: Calibrated Variational Inference for single-cell omics.
Author: Pierre Boyeau
Author-email: pierre.boyeau@gmail.com
Requires-Python: >=3.9,<3.13
Classifier: Programming Language :: Python :: 3
Classifier: Programming Language :: Python :: 3.9
Classifier: Programming Language :: Python :: 3.10
Classifier: Programming Language :: Python :: 3.11
Provides-Extra: dev
Provides-Extra: notebook
Requires-Dist: black (>=22.12.0,<23.0.0) ; extra == "dev"
Requires-Dist: fastcluster (>=1.2.6,<2.0.0)
Requires-Dist: flake8 (>=3.7.7) ; extra == "dev"
Requires-Dist: flax (>=0.7.5,<0.8.0)
Requires-Dist: isort (==5.11.5) ; extra == "dev"
Requires-Dist: jax (>=0.4.14,<0.5.0)
Requires-Dist: jupyterlab (>=4.0,<5.0) ; extra == "notebook"
Requires-Dist: ml-collections (>=0.1.1,<0.2.0)
Requires-Dist: numpyro (>=0.13.2,<0.14.0)
Requires-Dist: plotnine (>=0.12,<0.13)
Requires-Dist: pre-commit (>=3.0.2,<4.0.0) ; extra == "dev"
Requires-Dist: pytest (>=7.2.1,<8.0.0) ; extra == "dev"
Requires-Dist: scanpy (>=1.9.1,<2.0.0)
Requires-Dist: scikit-misc (>=0.1.4,<0.2.0)
Requires-Dist: torch (>=2.0.0,!=2.0.1,!=2.1.0)
Requires-Dist: xarray (>=2023.3.0,<2024.0.0)
